Workbook

Sheet Executive Summary
A1: PORTFOLIO CREATION & MANAGEMENT
A2: 6-Month Investment Horizon: Dec 2025 - Jun 2026
A4: PORTFOLIO OVERVIEW
A5: Total Investment Amount | B5: ₹1,000,000 | C5: Complete capital
A6: Deployed Capital | B6: ₹900,000 | C6: 90% in 15 stocks
A7: Cash Reserve (10%) | B7: ₹100,000 | C7: Safety buffer
A8: Number of Stocks | B8: 15 | C8: Diversified portfolio
A9: Investment Horizon | B9: 6 months | C9: Dec 2025 - Jun 2026
A11: KEY PERFORMANCE METRICS
A12: Expected Return (6M) | B12: ='MPT Analysis'!B4 -> 0.083162676 | C12: Target gain: 81635 rupees
A13: Expected Annual Return | B13: ='MPT Analysis'!B5 -> 0.17324138 | C13: Annualized projection
A14: Portfolio Volatility (σ) | B14: ='MPT Analysis'!B10 -> 0.1942 | C14: Standard deviation
A15: Portfolio Beta (β) | B15: ='MPT Analysis'!B12 -> 0.9056 | C15: Defensive positioning
A16: Sharpe Ratio | B16: ='MPT Analysis'!B17 -> 0.55067653 | C16: Good (>0.4 threshold)
A17: Treynor Ratio | B17: ='MPT Analysis'!B18 -> 0.11808898 | C17: Systematic risk return
A18: Jensen Alpha | B18: ='MPT Analysis'!B19 -> 0.034493382 | C18: Outperformance vs CAPM
A19: Information Ratio | B19: ='MPT Analysis'!B20 -> 2.8561399 | C19: Excellent (>2.0)
A21: Nifty 50 Expected Return | B21: 0.047 | C21: Benchmark comparison
A22: Annual Outperformance | B22: ='MPT Analysis'!B7 -> 0.10694138 | C22: Portfolio vs Nifty 50
A23: 6M Outperformance | B23: ='MPT Analysis'!B4 -> 0.083162676 | C23: Portfolio vs Nifty 50

Sheet Portfolio Holdings
B2: Portfolio Holdings
B4: Stock Name | C4: Ticker | D4: Sector | E4: Weight % | F4: Current Price | G4: Target 6M | H4: Upside % | I4: Beta | J4: Beta Contribution | K4: Volatility % | L4: Portfolio Volatality | M4: Dividend Yield % | N4: ROE % | O4: Investment | P4: Target Value | Q4: Gain
B6: HDFC Bank | C6: HDFCBANK | D6: Banking | E6: 8% | F6: 997 | G6: 1100 | H6: =(G6-F6)/F6 -> 0.10330993 | I6: 1.06 | J6: =E6*I6 -> 0.0848 | K6: 20% | L6: =K6*E6 -> 0.016 | M6: 0.011 | N6: 0.144 | O6: 80000 | P6: =O6+H6*O6 -> 88264.794 | Q6: =P6-O6 -> 8264.7944
B7: ICICI Bank | C7: ICICIBANK | D7: Banking | E7: 8% | F7: 1375 | G7: 1450 | H7: =(G7-F7)/F7 -> 0.054545455 | I7: 1.07 | J7: =E7*I7 -> 0.0856 | K7: 18% | L7: =K7*E7 -> 0.0144 | M7: 0.0081 | N7: 0.179 | O7: 80000 | P7: =O7+H7*O7 -> 84363.636 | Q7: =P7-O7 -> 4363.6364
B8: Bajaj Finance | C8: BAJFINANCE | D8: NBFC | E8: 8% | F8: 1017 | G8: 1200 | H8: =(G8-F8)/F8 -> 0.179941 | I8: 1.25 | J8: =E8*I8 -> 0.1 | K8: 25% | L8: =K8*E8 -> 0.02 | M8: 0.0044 | N8: 0.192 | O8: 80000 | P8: =O8+H8*O8 -> 94395.28 | Q8: =P8-O8 -> 14395.28
B9: Infosys | C9: INFY | D9: IT | E9: 8% | F9: 1599 | G9: 1850 | H9: =(G9-F9)/F9 -> 0.15697311 | I9: 0.887 | J9: =E9*I9 -> 0.07096 | K9: 22% | L9: =K9*E9 -> 0.0176 | M9: 0.027 | N9: 0.288 | O9: 80000 | P9: =O9+H9*O9 -> 92557.849 | Q9: =P9-O9 -> 12557.849
B10: TCS | C10: TCS | D10: IT | E10: 7% | F10: 3208 | G10: 3500 | H10: =(G10-F10)/F10 -> 0.091022444 | I10: 0.802 | J10: =E10*I10 -> 0.05614 | K10: 20% | L10: =K10*E10 -> 0.014 | M10: 0.0188 | N10: 0.524 | O10: 70000 | P10: =O10+H10*O10 -> 76371.571 | Q10: =P10-O10 -> 6371.5711
B11: Reliance Industries | C11: RELIANCE | D11: Energy | E11: 6% | F11: 1529 | G11: 1650 | H11: =(G11-F11)/F11 -> 0.079136691 | I11: 1.21 | J11: =E11*I11 -> 0.0726 | K11: 21% | L11: =K11*E11 -> 0.0126 | M11: 0.0036 | N11: 0.084 | O11: 60000 | P11: =O11+H11*O11 -> 64748.201 | Q11: =P11-O11 -> 4748.2014
B12: Larsen & Toubro | C12: LT | D12: Infrastructure | E12: 7% | F12: 3998 | G12: 4200 | H12: =(G12-F12)/F12 -> 0.050525263 | I12: 1.2 | J12: =E12*I12 -> 0.084 | K12: 0.22 | L12: =K12*E12 -> 0.0154 | M12: 0.0083 | N12: 0.166 | O12: 70000 | P12: =O12+H12*O12 -> 73536.768 | Q12: =P12-O12 -> 3536.7684
B13: Sun Pharma | C13: SUNPHARMA | D13: Pharma | E13: 7% | F13: 1776 | G13: 1900 | H13: =(G13-F13)/F13 -> 0.06981982 | I13: 0.579 | J13: =E13*I13 -> 0.04053 | K13: 0.2 | L13: =K13*E13 -> 0.014 | M13: 0.0089 | N13: 0.169 | O13: 70000 | P13: =O13+H13*O13 -> 74887.387 | Q13: =P13-O13 -> 4887.3874
B14: HUL | C14: HINDUNILVR | D14: FMCG | E14: 6% | F14: 2306 | G14: 2550 | H14: =(G14-F14)/F14 -> 0.10581093 | I14: 0.512 | J14: =E14*I14 -> 0.03072 | K14: 19% | L14: =K14*E14 -> 0.0114 | M14: 0.019 | N14: 0.207 | O14: 60000 | P14: =O14+H14*O14 -> 66348.656 | Q14: =P14-O14 -> 6348.6557
B15: ITC | C15: ITC | D15: FMCG | E15: 5% | F15: 401 | G15: 420 | H15: =(G15-F15)/F15 -> 0.047381546 | I15: 0.563 | J15: =E15*I15 -> 0.02815 | K15: 0.17 | L15: =K15*E15 -> 0.0085 | M15: 0.0357 | N15: 0.273 | O15: 50000 | P15: =O15+H15*O15 -> 52369.077 | Q15: =P15-O15 -> 2369.0773
B16: Bharti Airtel | C16: BHARTIARTL | D16: Telecom | E16: 5% | F16: 2090 | G16: 2300 | H16: =(G16-F16)/F16 -> 0.10047847 | I16: 0.82 | J16: =E16*I16 -> 0.041 | K16: 0.2 | L16: =K16*E16 -> 0.01 | M16: 0.0078 | N16: 0.232 | O16: 50000 | P16: =O16+H16*O16 -> 55023.923 | Q16: =P16-O16 -> 5023.9234
B17: BSE | C17: BSE | D17: Finance | E17: 4% | F17: 2716 | G17: 2900 | H17: =(G17-F17)/F17 -> 0.067746686 | I17: 1.4 | J17: =E17*I17 -> 0.056 | K17: 28% | L17: =K17*E17 -> 0.0112 | M17: 0.0022 | N17: 0.36 | O17: 40000 | P17: =O17+H17*O17 -> 42709.867 | Q17: =P17-O17 -> 2709.8675
B18: Mahindra & Mahindra | C18: M&M | D18: Auto | E18: 5% | F18: 3636 | G18: 3800 | H18: =(G18-F18)/F18 -> 0.04510451 | I18: 1.27 | J18: =E18*I18 -> 0.0635 | K18: 0.27 | L18: =K18*E18 -> 0.0135 | M18: 0.0069 | N18: 0.18 | O18: 50000 | P18: =O18+H18*O18 -> 52255.226 | Q18: =P18-O18 -> 2255.2255
B19: Tata Power | C19: TATAPOWER | D19: Utilities | E19: 4% | F19: 376 | G19: 400 | H19: =(G19-F19)/F19 -> 0.063829787 | I19: 1.71 | J19: =E19*I19 -> 0.0684 | K19: 0.24 | L19: =K19*E19 -> 0.0096 | M19: 0.0059 | N19: 0.11 | O19: 40000 | P19: =O19+H19*O19 -> 42553.191 | Q19: =P19-O19 -> 2553.1915
B20: Ashok Leyland | C20: ASHOKLEY | D20: Auto | E20: 2% | F20: 160 | G20: 170 | H20: =(G20-F20)/F20 -> 0.0625 | I20: 1.16 | J20: =E20*I20 -> 0.0232 | K20: 0.3 | L20: =K20*E20 -> 0.006 | M20: 0.0191 | N20: 0.288 | O20: 20000 | P20: =O20+H20*O20 -> 21250 | Q20: =P20-O20 -> 1250
J21: =SUM(J6:J20) -> 0.9056 | L21: =SUM(L6:L20) -> 0.1942 | O21: =SUM(O6:O20) -> 900000 | P21: =SUM(P6:P20) -> 981635.43
M22: # Fixed data vales are fetched from Screener and Top Stock Research

Sheet MPT Analysis
A1: MODERN PORTFOLIO THEORY ANALYSIS
A3: EXPECTED RETURNS | B3: Value | C3: Interpretation
A4: Portfolio Expected Return (6M) | B4: =('Portfolio Holdings'!P21-'Portfolio Holdings'!O21)/'Portfolio Holdings'!P21 -> 0.083162676 | C4: Target return over 6 months
A5: Portfolio Expected Return (Annual) | B5: =POWER(1+B4,2)-1 -> 0.17324138 | C5: Annualized expected return
A6: Nifty 50 Expected Return | B6: 4.70% | C6: Benchmark comparison
A7: Outperformance (Annual) | B7: =B5-B13 -> 0.10694138 | C7: Portfolio alpha generation
A9: RISK METRICS | B9: Value | C9: Interpretation
A10: Portfolio Volatility (σ) | B10: ='Portfolio Holdings'!L21 -> 0.1942 | C10: Standard deviation (annualized)
A11: Nifty 50 Volatility | B11: 15.00% | C11: Benchmark volatility
A12: Portfolio Beta (β) | B12: ='Portfolio Holdings'!J21 -> 0.9056 | C12: Portfolio moves 90.6% with market
A13: Risk-Free Rate | B13: 6.63% | C13: 10-year G-Sec yield
A14: Market Risk Premium | B14: 8.00% | C14: Historical equity risk premium
A16: RISK-ADJUSTED RETURN METRICS | B16: Value | C16: Interpretation
A17: Sharpe Ratio | B17: =B7/B10 -> 0.55067653 | C17: Good (>0.4) - Return per unit of risk
A18: Treynor Ratio | B18: =B7/B12 -> 0.11808898 | C18: Systematic risk-adjusted return
A19: Jensen Alpha | B19: =B5-(B13+B12*B14) -> 0.034493382 | C19: Outperformance vs CAPM
A20: Information Ratio | B20: =(B5-B6)/(B10-B11) -> 2.8561399 | C20: Excellent (>2.0) - Active management skill
A22: KEY INSIGHTS
A23: Portfolio Beta 0.906 | B23: Defensive positioning | C23: Lower volatility than market
A24: Sharpe Ratio 0.55 | B24: GOOD | C24: Strong risk-adjusted returns
A25: Information Ratio 2.86 | B25: EXCELLENT | C25: >2.0 indicates skilled management
A26: Jensen Alpha 3.45% | B26: POSITIVE | C26: Consistent outperformance

Sheet Profit Booking Strategy
A1: PROFIT BOOKING STRATEGY (3-TIER PYRAMID)
A3: TIER 1 - EARLY BOOKING | B3: Details
A4: Trigger | B4: Stock up 3-6% (~33% of upside to target) | C4: Lock in quick gains
A5: Quantity to Sell | B5: 33% of position | C5: Reduce average cost basis
A6: Use Proceeds | B6: Rebalance or add to cash
A8: TIER 2 - PARTIAL BOOKING | B8: Details
A9: Trigger | B9: Stock up 6-10% (~66% of upside to target) | C9: Secure core profits
A10: Quantity to Sell | B10: 50% of remaining (25% of original) | C10: Reduce exposure
A11: Use Proceeds | B11: Dividend reinvestment
A13: TIER 3 - FINAL EXIT | B13: Details
A14: Trigger | B14: Stock reaches target price (100% upside) | C14: Complete position exit
A15: Quantity to Sell | B15: Remaining 17% | C15: Final profit realization
A16: Use Proceeds | B16: Portfolio rebalancing
A18: PRIORITY BY PERFORMANCE | B18: Action | C18: Timeline
A19: HIGH (>15% up) | B19: Book profits immediately | C19: At Tier 1 + 2
A20: MEDIUM (8-15% up) | B20: Standard 3-tier approach | C20: Execute as planned
A21: LOW (<8% up) | B21: Hold longer | C21: Allow more time
A23: EXPECTED GAINS | B23: Amount | C23: Notes
A24: Total Portfolio Gains | B24: ='Portfolio Holdings'!P21-'Portfolio Holdings'!O21 -> 81635.429 | C24: From profit booking
A25: Average Gain per Stock | B25: =B24/15 -> 5442.3619 | C25: Mean across 15 stocks
A26: Median Gain per Stock | B26: =MEDIAN('Portfolio Holdings'!Q6:Q20) -> 4748.2014 | C26: Median across 15 stocks

Sheet Risk Management
A1: RISK MANAGEMENT PLAN - 30% MARKET FALL SCENARIO
A3: CURRENT RISK PROFILE | B3: Value | C3: Status
A4: Portfolio Beta | B4: ='MPT Analysis'!B12 -> 0.9056 | C4: DEFENSIVE (Lower than market)
A5: Portfolio Volatility | B5: 0.1942 | C5: ACCEPTABLE (<25% limit)
A6: Max Single Position | B6: 8% | C6: SAFE (<12% limit)
A7: Largest Sector Exposure | B7: 16% | C7: SAFE (<20% limit)
A8: Cash Reserve | B8: ₹100,000 | C8: 10% buffer maintained
A10: IF 30% MARKET FALL OCCURS | B10: Value | C10: Impact
A11: Market Decline | B11: -0.3 | C11: Nifty 50 down 30%
A12: Expected Portfolio Decline | B12: -0.27 | C12: Beta 0.906 × 30%
A13: Estimated Loss Amount | B13: =900000*B12 -> -243000 | C13: From ₹900,000 deployed
A14: Portfolio Value After Fall | B14: =900000+B13 -> 657000 | C14: Recovery opportunity
A15: Cash Buffer Available | B15: ₹100,000 | C15: For tactical buying
A16: Total Dry Powder | B16: =B15-B13 -> 343000 | C16: Emergency buying power
A18: IMMEDIATE ACTIONS (Day 1-2) | B18: Action | C18: Priority
A19: Do NOT Panic Sell | B19: Stick to strategy | C19: CRITICAL
A20: Review Fundamental Thesis | B20: Check thesis integrity | C20: HIGH
A21: Check Stop Loss Triggers | B21: Exit at -5% only | C21: AUTOMATIC
A22: Monitor Cash Position | B22: Ensure buffer maintained | C22: HIGH
A24: SHORT-TERM ACTIONS (Week 1-2) | B24: Action | C24: Priority
A25: Rebalance Portfolio | B25: Buy quality at lower prices | C25: HIGH
A26: Dollar-Cost Average | B26: Staged buying approach | C26: MEDIUM
A27: Deploy Cash | B27: 25-50% of buffer | C27: HIGH
A28: Update Risk Metrics | B28: Recalculate beta/volatility | C28: MEDIUM
A30: TACTICAL DEPLOYMENT PROTOCOL | B30: Market Decline | C30: Cash Deployed
A31: Conservative | B31: 10-15% fall | C31: Hold cash
... A43: Crisis Team | B43: Portfolio Manager, Risk Officer, Analyst | C43: STANDBY

Sheet Rebalancing Strategy
A1: REBALANCING STRATEGY & FRAMEWORK
A3: REBALANCING FREQUENCY | B3: Schedule | C3: Details
A4: PRIMARY | B4: Quarterly | C4: Dec 2025, Mar 2026, Jun 2026
A5: SECONDARY | B5: Monthly Reviews | C5: Every month-end for drift monitoring
A6: TERTIARY | B6: Event-Driven | C6: Triggered by major events/fundamentals
A8: REBALANCING CRITERIA | B8: Trigger | C8: Action
A9: Weight Deviation | B9: ±5% from target | C9: Rebalance immediately (HIGH)
A10: Performance Divergence | B10: >15% underperformance vs sector | C10: Review thesis, reduce 50% (MEDIUM)
A11: Volatility Spike | B11: >35% annualized | C11: Trim position 50% (HIGH)
A12: Fundamental Change | B12: Dividend cut, downgrade, mgmt change | C12: Exit or reduce (CRITICAL)
A13: Correlation Analysis | B13: >0.85 with portfolio | C13: Reduce one position (MEDIUM)
A14: Sector Rotation | B14: Quarterly momentum review | C14: Shift weights (MEDIUM-HIGH)
A16: SECTOR ALLOCATION | B16: Weight % | C16: Avg Return %
A17: Banking | B17: 16% | C17: =('Portfolio Holdings'!H6+'Portfolio Holdings'!H7)/2 -> 0.078927692
A18: IT | B18: 15% | C18: =('Portfolio Holdings'!H9+'Portfolio Holdings'!H10)/2 -> 0.12399778
A19: FMCG | B19: 11% | C19: =('Portfolio Holdings'!H14+'Portfolio Holdings'!H15)/2 -> 0.076596237
A20: NBFC | B20: 8% | C20: ='Portfolio Holdings'!H8 -> 0.179941
A21: Auto | B21: 7% | C21: =('Portfolio Holdings'!H18+'Portfolio Holdings'!H20)/2 -> 0.053802255
A22: Pharma | B22: 7% | C22: ='Portfolio Holdings'!H13 -> 0.06981982
A23: Infrastructure | B23: 7% | C23: ='Portfolio Holdings'!H12 -> 0.050525263
A24: Energy | B24: 6% | C24: ='Portfolio Holdings'!H11 -> 0.079136691
A25: Telecom | B25: 5% | C25: ='Portfolio Holdings'!H16 -> 0.10047847
A26: Finance | B26: 4% | C26: ='Portfolio Holdings'!H17 -> 0.067746686
A27: Utilities | B27: 4% | C27: ='Portfolio Holdings'!H19 -> 0.063829787
A29: 6-MONTH REBALANCING CALENDAR | B29: Date | C29: Event
A30: Initial Deployment | B30: Dec 2025 | C30: Deploy ₹900,000 across 15 stocks
A31: Monthly Review #1 | B31: Jan 2026 | C31: Performance tracking
A32: Monthly Review #2 | B32: Feb 2026 | C32: Drift monitoring
A33: QUARTERLY REBALANCE #1 | B33: Mar 2026 | C33: Major rebalancing event
A34: Monthly Review #3 | B34: Apr 2026 | C34: Mid-horizon assessment
A35: Monthly Review #4 | B35: May 2026 | C35: Final month preparation
A36: QUARTERLY REBALANCE #2 + EXIT | B36: Jun 2026 | C36: Portfolio exit & profit realization

Sheet Benchmarking
A1: PERFORMANCE BENCHMARKING FRAMEWORK
A3: PRIMARY BENCHMARK | B3: Details
A4: Index Name | B4: Nifty 50 | C4: Largest 50 companies in India
A5: Expected Return | B5: 4.70% (Annual) | C5: 2.35% (6-Month)
A6: Volatility | B6: 15.00% | C6: Market standard
A8: SECONDARY BENCHMARKS | B8: Annual Return | C8: Volatility
A9: Nifty IT | B9: 24.80% | C9: 21.00%
A10: Nifty Bank | B10: 15.78% | C10: 19.00%
A11: Nifty FMCG | B11: 15.32% | C11: 19.50%
A12: Nifty Auto | B12: 10.76% | C12: 29.50%
A13: Nifty Pharma | B13: 13.96% | C13: 21.00%
A14: Nifty Infrastructure | B14: 10.10% | C14: 23.00%
A16: PORTFOLIO VS BENCHMARKS | B16: Portfolio | C16: Nifty 50
A17: Expected Return (6M) | B17: ='MPT Analysis'!B4 -> 0.083162676 | C17: 2.35%
A18: Expected Return (Annual) | B18: ='MPT Analysis'!B5 -> 0.17324138 | C18: 4.70%
A19: Volatility | B19: ='MPT Analysis'!B10 -> 0.1942 | C19: 15.00%
A20: Beta | B20: ='MPT Analysis'!B12 -> 0.9056 | C20: 1.000
A21: Sharpe Ratio | B21: ='MPT Analysis'!B17 -> 0.55067653 | C21: 0.1927
A23: BENCHMARKING FREQUENCY | B23: Schedule | C23: Action
A24: Daily | B24: Monitor index levels | C24: Track P&L & correlation
A25: Weekly | B25: Weekly comparison | C25: Portfolio vs index change
A26: Monthly | B26: Detailed analysis | C26: Performance report
A27: Quarterly | B27: Comprehensive review | C27: Rebalancing decision
A29: PERFORMANCE THRESHOLDS | B29: Trigger | C29: Action
A30: Return <Target by 2% | B30: Review & increase monitoring | C30: MEDIUM
A31: Underperform Nifty >5% | B31: Rebalance & reassess | C31: HIGH
A32: Volatility >25% | B32: Reduce high-beta | C32: HIGH
A33: Drawdown >15% | B33: Activate crisis protocol | C33: CRITICAL

Sheet Monitoring Dashboard
A1: PORTFOLIO MONITORING DASHBOARD
A3: DAILY MONITORING METRICS | B3: Target | C3: Status
A4: Portfolio Value | B4: ₹900,000 | C4: Current
A5: Portfolio Return (6M%) | B5: =Benchmarking!B17 -> 0.083162676 | C5: Target
A6: Portfolio Beta | B6: =Benchmarking!B20 -> 0.9056 | C6: Defensive
A7: Portfolio Volatility | B7: =Benchmarking!B19 -> 0.1942 | C7: Within limit
A8: Maximum Drawdown | B8: Monitor | C8: Target: <15%
A9: Nifty 50 Level | B9: Monitor | C9: Daily tracking
A10: Dividend Received | B10: ₹0 | C10: Reinvest when received
A11: Cash Position | B11: ₹100,000 | C11: Maintain 10% buffer
A13: MONTHLY REVIEW CHECKLIST | B13: Frequency | C13: Owner
A14: Performance vs Target | B14: Monthly | C14: Portfolio Manager
A15: Performance vs Nifty 50 | B15: Monthly | C15: Research Analyst
A16: Stock Fundamental Updates | B16: Monthly | C16: Research Team
A17: Volatility Trends | B17: Monthly | C17: Risk Officer
A18: Weight Deviation Check | B18: Monthly | C18: Portfolio Manager
A19: Beta Recalculation | B19: Monthly | C19: Quant Analyst
A20: Dividend Tracking | B20: Monthly | C20: Operations
... A25: Portfolio Initiation | B25: Dec 2025 | C25: ₹900,000
A26: Month 1-2 Review | B26: Jan-Feb 2026 | C26: ='Profit Booking Strategy'!B24/3+C25 -> 927211.81
A27: Q1 Rebalancing | B27: Mar 2026 | C27: ='Profit Booking Strategy'!B24/2+'Monitoring Dashboard'!C25 -> 940817.71
A28: Month 4-5 Review | B28: Apr-May 2026 | C28: ='Profit Booking Strategy'!B24/6*5+'Monitoring Dashboard'!C25 -> 968029.52
A29: Final Exit | B29: Jun 2026 | C29: ='Profit Booking Strategy'!B24+'Monitoring Dashboard'!C25 -> 981635.43

Sheet Action Plan Timeline
A1: EXECUTION TIMELINE & ACTION PLAN (6-MONTH HORIZON)
A3: Month | B3: Calendar Date | C3: Key Actions | D3: Key Metrics
A4: 0 | B4: Dec 2025 | C4: Portfolio Initiation - Deploy ₹900,000 across 15 stocks | D4: Initial P&L = 0%
A5: 1 | B5: Jan 2026 | C5: Monthly Review - Performance tracking, dividend monitoring | D5: Monthly Return vs Target
A6: 2 | B6: Feb 2026 | C6: Monthly Review - Check weight deviation, sector momentum | D6: Volatility trends
A7: 3 | B7: Mar 2026 | C7: QUARTERLY REBALANCE #1 - Trim winners, buy losers | D7: Rebalancing P&L
A8: 4 | B8: Apr 2026 | C8: Monthly Review - Mid-horizon, profit booking tier-2 | D8: Position performance
A9: 5 | B9: May 2026 | C9: Monthly Review - Final month, trend analysis | D9: Profit booking tracking
A10: 6 | B10: Jun 2026 | C10: PORTFOLIO EXIT & Q2 REBALANCE - Realize all gains | D10: Final Return = 8.32%
A12: QUARTERLY MILESTONES | B12: Target Date | C12: Expected Return
A13: Q0 Initiation | B13: Dec 2025 | C13: 0%
A14: Q1 Checkpoint | B14: Mar 2026 | C14: ='MPT Analysis'!B4/2 -> 0.041581338
A15: Q2 Exit | B15: Jun 2026 | C15: ='MPT Analysis'!B4 -> 0.083162676

Sheet Key Metrics Summary
A1: KEY PORTFOLIO METRICS & CALCULATIONS
A3: PORTFOLIO PERFORMANCE | B3: Value | C3: Details
A4: Total Investment Amount | B4: ₹1,000,000 | C4: Complete capital
A5: Deployed Capital | B5: ₹900,000 | C5: 90% in stocks
A6: Cash Reserve | B6: ₹100,000 | C6: 10% safety buffer
A7: Expected Return (6M) | B7: 8.16% | C7: ₹73,440 absolute gain
A8: Expected Return (Annual) | B8: 16.32% | C8: Annualized projection
A9: Nifty 50 Expected Return | B9: 4.70% | C9: Benchmark
A10: Annual Outperformance | B10: 11.62% | C10: Portfolio vs Nifty 50
A12: RISK PROFILE | B12: Value | C12: Status
A13: Portfolio Volatility | B13: =Benchmarking!B19 -> 0.1942 | C13: Standard deviation
A14: Portfolio Beta | B14: =Benchmarking!B20 -> 0.9056 | C14: Defensive (<1.0)
A15: Max Single Position | B15: 8% | C15: Safe (<12%)
A16: Largest Sector | B16: 16% | C16: Banking & Finance
A17: Risk Rating | B17: MEDIUM-HIGH | C17: Balanced growth
A19: RISK-ADJUSTED RETURNS | B19: Value | C19: Benchmark
A20: Sharpe Ratio | B20: ='MPT Analysis'!B17 -> 0.55067653 | C20: Good (>0.4)
A21: Treynor Ratio | B21: ='MPT Analysis'!B18 -> 0.11808898 | C21: Systematic risk
A22: Jensen Alpha | B22: ='MPT Analysis'!B19 -> 0.034493382 | C22: Outperformance
A23: Information Ratio | B23: ='MPT Analysis'!B20 -> 2.8561399 | C23: Excellent (>2.0)
A25: 30% MARKET FALL SCENARIO | B25: Value | C25: Impact
A26: Expected Decline | B26: 0.27 | C26: Beta × 30% fall
A27: Loss Amount | B27: ='Risk Management'!B13 -> -243000 | C27: From ₹900,000
A28: Remaining Value | B28: ='Risk Management'!B14 -> 657000 | C28: After 30% fall
A29: Cash Available | B29: ₹100,000 | C29: Safety buffer
A30: Total Buying Power | B30: ='Risk Management'!B16 -> 343000 | C30: Emergency capital
A32: PROFIT BOOKING TARGETS | B32: Value | C32: Description
A33: Expected Portfolio Gains | B33: ='Profit Booking Strategy'!B24 -> 81635.429 | C33: From profit booking
A34: Average Gain per Stock | B34: ='Profit Booking Strategy'!B25 -> 5442.3619 | C34: Mean across 15 stocks
A35: Median Gain per Stock | B35: ='Profit Booking Strategy'!B26 -> 4748.2014 | C35: Median across 15 stocks
A36: Tier 1 Avg (33% position) | B36: =(0.33*'Profit Booking Strategy'!B25) -> 1795.9794 | C36: Early booking gains
A37: Tier 2 Avg (50% position) | B37: =0.5*'Profit Booking Strategy'!B25 -> 2721.181 | C37: Partial booking gains
A38: Tier 3 Avg (17% position) | B38: =0.17*'Profit Booking Strategy'!B25 -> 925.20153 | C38: Final exit gains
